pycla/__init__.py
pycla/bin/__init__.py
pycla/bin/cla.py
pycla/bin/libcla.so
pycla/bin/libcla.so.1.2.0
pycla/core/__init__.py
pycla/core/cuda_device.py
pycla/core/matrix.py
pycla/core/vector.py
pycla-1.2.1.dist-info/licenses/LICENSE
pycla-1.2.1.dist-info/METADATA
pycla-1.2.1.dist-info/WHEEL
pycla-1.2.1.dist-info/top_level.txt
pycla-1.2.1.dist-info/RECORD
