Metadata-Version: 2.4
Name: pycla
Version: 1.2.1
Summary: CLA is a simple toy library for basic vector/matrix operations written C + CUDA with a Python API.
Project-URL: repository, https://github.com/moesio-f/cla
Keywords: linear algebra,vector,matrix,c,ctypes,cuda,gpu
Classifier: Development Status :: 5 - Production/Stable
Classifier: Environment :: GPU :: NVIDIA CUDA :: 12
Classifier: Operating System :: POSIX :: Linux
Classifier: Intended Audience :: Developers
Classifier: Programming Language :: Python :: 3.13
Classifier: Programming Language :: Python :: 3.12
Classifier: Programming Language :: Python :: 3.11
Classifier: Programming Language :: Python :: 3.10
Classifier: Programming Language :: C
Requires-Python: >=3.10
License-File: LICENSE
Dynamic: license-file
